fastapiali_classes/__init__.py
fastapiali_classes/buonicovid/__init__.py
fastapiali_classes/buonicovid/acquisizione_buoni_dettagli.py
fastapiali_classes/buonicovid/acquisizione_buoni_testata.py
fastapiali_classes/buonicovid/impresa.py
fastapiali_classes/buonicovid/taglio_buono.py
fastapiali_classes/richiestevolantini/__init__.py
fastapiali_classes/richiestevolantini/linea_vol.py
fastapiali_classes/richiestevolantini/offerta_volantini.py
fastapiali_classes/richiestevolantini/richieste_volantini.py
fastapiali_classes/richiestevolantini/vol_PV.py
fastapiali_classes/utilities/__init__.py
fastapiali_classes/utilities/punto_vendita.py
fastapiali_classes-2.2.31.dist-info/LICENSE
fastapiali_classes-2.2.31.dist-info/METADATA
fastapiali_classes-2.2.31.dist-info/WHEEL
fastapiali_classes-2.2.31.dist-info/top_level.txt
fastapiali_classes-2.2.31.dist-info/RECORD
