Metadata-Version: 2.1
Name: fastapiali-classes
Version: 2.2.31
Summary: Classi per poter creare oggeti da usare con fastapi
Home-page: https://github.com/giaca95/Fastapiali-classes
Author: giaca95
Author-email: giacomo_callegaro.95@libero.it
License: MIT
Download-URL: https://github.com/giaca95/Fastapiali-classes.git
Platform: UNKNOWN
Classifier: Programming Language :: Python :: 3
Classifier: License :: OSI Approved :: MIT License
Classifier: Operating System :: OS Independent
Requires-Python: >=3.7
Requires-Dist: SQLAlchemy (>=1.3.22)
Requires-Dist: Pydantic (>=1.7.3)
Requires-Dist: fastapi-modules (>=2.2.9)
Requires-Dist: FastAPI-SQLAlchemy (>=0.2.1)
